holoocean/__init__.py
holoocean/packagemanager.py
holoocean-0.5.8.dist-info/METADATA
holoocean-0.5.8.dist-info/WHEEL
holoocean-0.5.8.dist-info/top_level.txt
holoocean-0.5.8.dist-info/RECORD
