Metadata-Version: 2.1
Name: holoocean
Version: 0.5.8
Summary: An Open-Source Simulator for Marine Robotic Autonomy
Home-page: https://holoocean.readthedocs.io/
Author: BYU Field Robotic Systems Lab, Joshua Mangelson, (and many others)
Author-email: mangelson@byu.edu
License: MIT License (BYU Client Code), Unreal EULA for Unreal Code
Requires-Python: >=3.6
Requires-Dist: numpy
Requires-Dist: posix-ipc >=1.0.0 ; platform_system == "Linux"
Requires-Dist: pywin32 <=228 ; platform_system == "Windows"
